mermkit/__init__.py
mermkit/py.typed
mermkit-0.1.0.dist-info/METADATA
mermkit-0.1.0.dist-info/WHEEL
mermkit-0.1.0.dist-info/RECORD
